databases/__init__.py
databases/core.py
databases/importer.py
databases/interfaces.py
databases/py.typed
databases/backends/__init__.py
databases/backends/aiopg.py
databases/backends/common.py
databases/backends/mysql.py
databases/backends/postgres.py
databases/backends/sqlite.py
databases_extended-0.4.1.data/data/LICENSE.md
databases_extended-0.4.1.dist-info/LICENSE.md
databases_extended-0.4.1.dist-info/METADATA
databases_extended-0.4.1.dist-info/WHEEL
databases_extended-0.4.1.dist-info/top_level.txt
databases_extended-0.4.1.dist-info/RECORD
