Metadata-Version: 2.1
Name: databases-extended
Version: 0.4.1
Summary: Async database support for Python.
Home-page: https://github.com/encode/databases
Author: Tom Christie
Author-email: tom@tomchristie.com
License: BSD
Platform: UNKNOWN
Classifier: Development Status :: 3 - Alpha
Classifier: Environment :: Web Environment
Classifier: Intended Audience :: Developers
Classifier: License :: OSI Approved :: BSD License
Classifier: Operating System :: OS Independent
Classifier: Topic :: Internet :: WWW/HTTP
Classifier: Programming Language :: Python :: 3
Classifier: Programming Language :: Python :: 3.6
Classifier: Programming Language :: Python :: 3.7
Requires-Python: >=3.6
Requires-Dist: sqlalchemy
Requires-Dist: aiocontextvars ; python_version < "3.7"
Provides-Extra: mysql
Requires-Dist: aiomysql ; extra == 'mysql'
Requires-Dist: pymysql ; extra == 'mysql'
Provides-Extra: postgresql
Requires-Dist: asyncpg ; extra == 'postgresql'
Requires-Dist: psycopg2 ; extra == 'postgresql'
Provides-Extra: postgresql_aiopg
Requires-Dist: aiopg ; extra == 'postgresql_aiopg'
Provides-Extra: sqlite
Requires-Dist: aiosqlite ; extra == 'sqlite'
